llmdeploy/__init__.py
llmdeploy/cli.py
llmdeploy/manager.py
llmdeploy/model_manager.py
llmdeploy/server.py
deploy_llm-0.1.5.dist-info/METADATA
deploy_llm-0.1.5.dist-info/WHEEL
deploy_llm-0.1.5.dist-info/entry_points.txt
deploy_llm-0.1.5.dist-info/top_level.txt
deploy_llm-0.1.5.dist-info/RECORD
