Metadata-Version: 2.1
Name: deploy-llm
Version: 0.1.5
Summary: CLI tool for deploying and running models from Ollama and Hugging Face
Author: Ankit Gupta
Classifier: Programming Language :: Python :: 3
Classifier: License :: OSI Approved :: MIT License
Classifier: Operating System :: OS Independent
Requires-Python: >=3.7
Requires-Dist: click
Requires-Dist: torch
Requires-Dist: transformers
